examples/insert_pdf_file.py
examples/memories_demo.py
kinic_py/__init__.py
kinic_py/_lib.cpython-313-darwin.so
kinic_py/memories.py
kinic_py-0.1.2.dist-info/licenses/LICENSE
kinic_py-0.1.2.dist-info/METADATA
kinic_py-0.1.2.dist-info/WHEEL
kinic_py-0.1.2.dist-info/top_level.txt
kinic_py-0.1.2.dist-info/RECORD
