Metadata-Version: 2.4
Name: kinic-py
Version: 0.1.2
Summary: Python bindings for the Kinic CLI Rust core
Author: Kinic
License: Proprietary
Keywords: kinic,internet-computer,cli,bindings
Classifier: Programming Language :: Python :: 3
Classifier: Programming Language :: Rust
Classifier: License :: Other/Proprietary License
Classifier: Operating System :: OS Independent
Requires-Python: >=3.9
License-File: LICENSE
Dynamic: license-file
